<?xml version="1.0" encoding="utf-8"?>
<openerp>
	<data>

	<!-- 02/04/2014 (fuc) Creacion menu Procesos intermedios
		(+) Crear submenu "Procesos Intermedios" con "Contenido de Project"
		(+) 22/04/2014 - Agregar "Costos"
		(+) 22/04/2014 - Agregar "Tareas"
	-->

	<!--
	<menuitem id="mn_estudios_procesos" name="Procesos intermedios" parent="mn_estudios" action="" sequence="5"/>
	<menuitem id="sbmn_proyectos_procesos" name="Proyectos" parent="mn_estudios_procesos" action="project.open_view_project_all" sequence="1"/>
	<menuitem id="sbmn_tareas_procesos" name="Tareas" parent="mn_estudios_procesos" action="project.action_view_task" sequence="2"/>
	-->
	<!-- FVE - 08/julio/2014: se quito debido a que el menú se pasó a estudios/menu/estudios.xml -->

	<!-- 23/06/2014 (fuc) Menu procesos intermedios - tareas
		(-) Agregar campo "Cuotas x Hora"
		(-) Agregar campo "Fase" de tipo combo con:
			- Previo
			- En proceso
		(-) Cambiar etiqueta "Etapa" por "Estatus"
		(-) Agregar permisos para delegar
		(-) Eliminar campo "Cliente"
	-->

        <!-- <record id="view_arranques_tree" model="ir.ui.view">
            <field name="name">project.arranques.tree</field>
            <field name="model">project.arranques</field>
            <field eval="1" name="priority"/>
            <field name="arch" type="xml">
                <tree string="Administración de arranques">
                    <field name="name_arranques" string="Nombre del estudio"/>
                    <field name="fecha_solicitud" string="Fecha de solicitud"/>
                    <field name="fecha_entrega" string="Fecha de entrega"/>
                    <field name="tarea_responsable_id" string="Responsable"/>
                    <field name="tarea_estatus" string="Estatus"/>
                    <field name="material_product_id" string="Material"/>
                </tree>
            </field>
        </record> -->

    </data>
</openerp>
